funcbygpt/__init__.py
funcbygpt-0.0.2.dist-info/METADATA
funcbygpt-0.0.2.dist-info/WHEEL
funcbygpt-0.0.2.dist-info/top_level.txt
funcbygpt-0.0.2.dist-info/RECORD
