Metadata-Version: 2.1
Name: funcbygpt
Version: 0.0.2
Summary: tell the function what to do and gpt will write the code
Home-page: https://github.com/emresvd/funcbygpt
Author: emresvd
License: MIT
Keywords: gpt,openai,wrapper
Classifier: Development Status :: 4 - Beta
Classifier: Intended Audience :: Developers
Classifier: License :: OSI Approved :: MIT License
Classifier: Programming Language :: Python :: 3
Classifier: Topic :: Software Development :: Libraries :: Python Modules
Classifier: Operating System :: OS Independent
Requires-Dist: openai (==0.27.2)
Requires-Dist: python-dotenv (==0.21.1)
